aif_workflow_helper/__init__.py
aif_workflow_helper/cli/__init__.py
aif_workflow_helper/cli/main.py
aif_workflow_helper/core/__init__.py
aif_workflow_helper/core/delete.py
aif_workflow_helper/core/download.py
aif_workflow_helper/core/formats.py
aif_workflow_helper/core/upload.py
aif_workflow_helper/utils/__init__.py
aif_workflow_helper/utils/logging.py
aif_workflow_helper/utils/validation.py
aif_workflow_helper-0.3.1.dist-info/WHEEL
aif_workflow_helper-0.3.1.dist-info/entry_points.txt
aif_workflow_helper-0.3.1.dist-info/METADATA
aif_workflow_helper-0.3.1.dist-info/RECORD
