Metadata-Version: 2.3
Name: aif-workflow-helper
Version: 0.3.1
Summary: Azure AI Foundry dev workflow helpers
Keywords: azure,ai,agents,workflow,automation
Author: Pete Roden
Author-email: Pete Roden <pete.roden@live.com>
License: MIT
Classifier: Programming Language :: Python :: 3
Classifier: License :: OSI Approved :: MIT License
Classifier: Operating System :: OS Independent
Requires-Dist: azure-ai-projects
Requires-Dist: azure-ai-agents
Requires-Dist: azure-identity
Requires-Dist: pyyaml
Requires-Dist: python-frontmatter
Requires-Dist: pytest>=7.0.0 ; extra == 'dev'
Requires-Dist: pytest-cov>=4.0.0 ; extra == 'dev'
Requires-Dist: pytest-mock>=3.10.0 ; extra == 'dev'
Requires-Python: >=3.10
Project-URL: Homepage, https://github.com/peteroden/aif-workflow-helper
Project-URL: Source, https://github.com/peteroden/aif-workflow-helper
Provides-Extra: dev
